meterstick/__init__.py
meterstick/confidence_interval_display.py
meterstick/diversity.py
meterstick/metrics.py
meterstick/models.py
meterstick/operations.py
meterstick/sql.py
meterstick/utils.py
meterstick-1.5.8.dist-info/licenses/LICENSE
meterstick-1.5.8.dist-info/METADATA
meterstick-1.5.8.dist-info/WHEEL
meterstick-1.5.8.dist-info/top_level.txt
meterstick-1.5.8.dist-info/RECORD
