Metadata-Version: 2.4
Name: meterstick
Version: 1.5.8
Summary: A grammar of data analysis
Author-email: Xunmo Yang <xunmo@google.com>, Dennis Sun <dlsun@google.com>, Taylor Pospisil <taylorpospisil@google.com>
License-Expression: Apache-2.0
Project-URL: Homepage, https://github.com/google/meterstick
Project-URL: Bug Tracker, https://github.com/google/meterstick/issues
Classifier: Development Status :: 5 - Production/Stable
Classifier: Framework :: IPython
Classifier: Framework :: Jupyter
Classifier: Intended Audience :: Science/Research
Classifier: Programming Language :: Python
Classifier: Programming Language :: Python :: 3
Classifier: Programming Language :: SQL
Requires-Python: >=3.6
License-File: LICENSE
Dynamic: license-file
